Workbook

Sheet ItemizedPurchase
A1: Date | B1: Time | C1: Location | D1: Online | E1: InStore | F1: OrderTransID_ReceiptID | G1: ItemID | H1: Item | I1: Qty | J1: Qty_units | K1: PriceRaw
A2: 46022 | B2: 0.29166667 | C2: Amazon | D2: 1 | F2: 111-8892052-0363409 | H2: TAGMORE M12X1.5 Lug Nuts - 20pcs OEM Wheel Lug Nuts Compatible with 2009-18 Focus/2012-18 Fusion/2013-2020 Escape/2018+ EcoSport/2011-19 Fiesta, Chrome Acorn Wheel Nuts | K2: 19.99
A3: 46022 | B3: 0.29166667 | C3: Amazon | D3: 1 | F3: 111-8892052-0363409 | H3: Sales Tax | K3: 1.6
A4: 46022 | B4: 0.29166667 | C4: CollegeInvest | D4: 1 | H4: Isabella first semester success gift! $550 = ($90/A)(6 A) + ($5/Pass)(2 Pass) | K4: 550
A5: 46021 | B5: 0.83333333 | C5: Allegacy FCU | D5: 1 | H5: Hong Kong Station reimbursement | I5: 1 | J5: cnt | K5: -130
A6: 46021 | B6: 0.71041667 | C6: Hong Kong Station | D6: 1 | F6: #142 | G6: #17 | H6: Orange chicken | K6: 15.95
A7: 46021 | B7: 0.71041667 | C7: Hong Kong Station | D7: 1 | F7: #142 | G7: #01 | H7: Beef Chao Fan | K7: 16.95
A8: 46021 | B8: 0.71041667 | C8: Hong Kong Station | D8: 1 | F8: #142 | G8: #07 | H8: Salt and Pepper Tofu | K8: 15.95
A9: 46021 | B9: 0.71041667 | C9: Hong Kong Station | D9: 1 | F9: #142 | G9: #14 | H9: Salt and Pepper Shrimp (no head!) | K9: 17.95
A10: 46021 | B10: 0.71041667 | C10: Hong Kong Station | D10: 1 | F10: #142 | G10: #28 | H10: Garlic Yu Choy | K10: 15.95
A11: 46021 | B11: 0.71041667 | C11: Hong Kong Station | D11: 1 | F11: #142 | H11: Eggplant in Garlic Sauce (contains minced pork) | K11: 17.95
A12: 46021 | B12: 0.71041667 | C12: Hong Kong Station | D12: 1 | F12: #142 | G12: #06 | H12: Szechuan style spicy chicken (bone in) | K12: 17.95
A13: 46021 | B13: 0.71041667 | C13: Hong Kong Station | D13: 1 | F13: #142 | H13: 5 White Rice | K13: 0
A14: 46021 | B14: 0.71041667 | C14: Hong Kong Station | D14: 1 | F14: #142 | H14: Convenience Fee | K14: 1
A15: 46021 | B15: 0.71041667 | C15: Hong Kong Station | D15: 1 | F15: #142 | H15: Tax | K15: 8.01
A16: 46021 | C16: Pottery Barn | D16: 1 | F16: 353142751315 | H16: Mary Wu Christmas gift to Tovi (blanket cover) | I16: 1 | J16: cnt | K16: -81.46
A17: 46021 | C17: Amazon | D17: 1 | F17: GMCB-250121-1191665 | H17: **PENDING** Lydia Placeholder for GM 'retirement' gift >w< | I17: 4 | J17: cnt | K17: =280-105-83
A18: 46021 | C18: BELLA Health + Wellness | D18: 1 | H18: 10/27 Tovi Bilirubin visit ft. Drew Miller, PA | I18: 1 | J18: cnt | K18: 478
A19: 46021 | C19: Urgent Care Solutions GLE | D19: 1 | G19: 2025258BU0560 | H19: 9/7 Elisheva throw-up/diarrhea urgent care visit | I19: 1 | J19: cnt | K19: 117.06
A20: 46021 | C20: Labcorp OnDemand | G20: 2025115BI1381 | H20: 4/17 Lydia prenatal urine culture | I20: 1 | J20: cnt | K20: 14.71
A21: 46021 | H21: PLACEHOLDER: gate for sheva (100) | K21: 100
A22: 46021 | H22: Gift from Mary and Joseph Wu | I22: 1 | J22: cnt | K22: -79.99
A23: 46020 | B23: 0.40972222 | C23: StackSocial | D23: 1 | F23: 24804740 | G23: G4BB6-MPYWP-VKYPB-JMTDD-NV9JK | H23: Microsoft Windows 11 -- 2021 Office Suite | I23: 1 | J23: cnt | K23: 34.97
A24: 46020 | B24: 0.40972222 | C24: StackSocial | D24: 1 | F24: 24804740 | H24: Handling | K24: 1.99
A25: 46020 | B25: 0.40972222 | C25: StackSocial | D25: 1 | F25: 24804740 | H25: Tax | I25: 1 | J25: cnt | K25: 3.2
A26: 46020
A27: 46019
A28: 46018
A29: 46017 | B29: 0.41805556 | C29: Speedway | E29: 1 | H29: Subaru Gas ? Gallons @ $?/gal | K29: 16.94
A30: 46017 | B30: 0.41666667 | C30: Speedway | E30: 1 | H30: Subaru Gas ? Gallons @ $?/gal | K30: 15.28
A31: 46015 | B31: 0.35625 | C31: Two Chicks and a Hippie | E31: 1 | H31: Sticky Buns in Pagosa Springs | K31: 13.36
A32: 46015 | B32: 0.34861111 | C32: Two Chicks and a Hippie | E32: 1 | H32: Breakfast in Pagosa Springs | K32: 84.05
A33: 46015 | B33: 0.29166667 | C33: US Tax Witholding | D33: 1 | F33: RTX_Paycheck_25_52 | H33: Federal Income Tax | K33: 467.33
A34: 46015 | B34: 0.29166667 | C34: US Tax Witholding | D34: 1 | F34: RTX_Paycheck_25_52 | H34: Social Security Tax | K34: 353.38
A35: 46015 | B35: 0.29166667 | C35: US Tax Witholding | D35: 1 | F35: RTX_Paycheck_25_52 | H35: Medicare Tax | K35: 82.65
A36: 46015 | B36: 0.29166667 | C36: Raytheon | D36: 1 | F36: RTX_Paycheck_25_52 | G36: XXXX3523 | H36: Net Paycheck [Dec 6 - Dec 19] | K36: 3298.03
A37: 46015 | B37: 0.29166667 | C37: Raytheon | D37: 1 | F37: RTX_Paycheck_25_52 | H37: RTX Direct Deposit -- cancelling offset | K37: -3298.03
A38: 46015 | B38: 0.29166667 | C38: Raytheon | D38: 1 | F38: RTX_Paycheck_25_52 | H38: Gross Paycheck [Dec 6 - Dec 19] ($62.5000/hr) | K38: -5948.83
A39: 46015 | B39: 0.29166667 | C39: Raytheon | D39: 1 | F39: RTX_Paycheck_25_52 | H39: Ed(ucation) Assi(tance) Offset | K39: 948.83
A40: 46015 | B40: 0.29166667 | C40: Parents Gift Account | D40: 1 | F40: RTX_Paycheck_25_52 | G40: XXXX7146 | H40: Contribution to Parents Gift Account | K40: 0.01
A41: 46015 | B41: 0.29166667 | C41: HSA | D41: 1 | F41: RTX_Paycheck_25_52 | H41: Personal contribution to HSA | K41: 115.72
A42: 46015 | B42: 0.29166667 | C42: Delta Dental | D42: 1 | F42: RTX_Paycheck_25_52 | H42: Dental Insurance | K42: 4.26
A43: 46015 | B43: 0.29166667 | C43: CO Tax Witholding | D43: 1 | F43: RTX_Paycheck_25_52 | H43: CO State Income Tax | K43: 220.57
A44: 46015 | B44: 0.29166667 | C44: CO Tax Witholding | D44: 1 | F44: RTX_Paycheck_25_52 | H44: CO Paid Family Leave Insurance | K44: 26.77
A45: 46015 | B45: 0.29166667 | C45: Anthem BcBs | D45: 1 | F45: RTX_Paycheck_25_52 | H45: Medical Insurance | K45: 131.28
A46: 46015 | B46: 0.29166667 | C46: Alight | D46: 1 | F46: RTX_Paycheck_25_52 | H46: 401k Basic -- Traditional | K46: 300
A47: 46015 | B47: 0.29166667 | C47: Alight | D47: 1 | F47: RTX_Paycheck_25_52 | H47: Roth 401k Basic | K47: 0
A48: 46015 | B48: 0.29166667 | C48: US Tax Witholding | D48: 1 | F48: RTX_Paycheck_25_53 | H48: Federal Income Tax | K48: 155.1
A49: 46015 | B49: 0.29166667 | C49: US Tax Witholding | D49: 1 | F49: RTX_Paycheck_25_53 | H49: Social Security Tax | K49: 46.1
A50: 46015 | B50: 0.29166667 | C50: US Tax Witholding | D50: 1 | F50: RTX_Paycheck_25_53 | H50: Medicare Tax | K50: 10.87
A51: 46015 | B51: 0.29166667 | C51: Raytheon | D51: 1 | F51: RTX_Paycheck_25_53 | G51: XXXX3523 | H51: Net Paycheck [Bonus] | K51: 458.13
A52: 46015 | B52: 0.29166667 | C52: Raytheon | D52: 1 | F52: RTX_Paycheck_25_53 | H52: RTX Direct Deposit -- cancelling offset | K52: -458.13
A53: 46015 | B53: 0.29166667 | C53: Raytheon | D53: 1 | F53: RTX_Paycheck_25_53 | H53: Gross Paycheck [Bonus] ($62.5000/hr) | K53: -750
A54: 46015 | B54: 0.29166667 | C54: CO Tax Witholding | D54: 1 | F54: RTX_Paycheck_25_53 | H54: CO State Income Tax | K54: 31.02
A55: 46015 | B55: 0.29166667 | C55: CO Tax Witholding | D55: 1 | F55: RTX_Paycheck_25_53 | H55: CO Paid Family Leave Insurance | K55: 3.38
A56: 46015
A57: 46014
A58: 46014
A59: 46013 | B59: 0.29166667 | C59: Xcel Energy | D59: 1 | F59: 955308634_ | H59: Franchise Fee 3.00% | K59: =1.73+0.97
A60: 46013 | B60: 0.29166667 | C60: Xcel Energy | D60: 1 | F60: 955308634_ | H60: Electricity 10/27/25 - 11/25/25 | I60: 339 | J60: kWh | K60: 57.9
A61: 46013 | B61: 0.29166667 | C61: Xcel Energy | D61: 1 | F61: 955308634_ | H61: Natural Gas 10/29/25 - 12/01/25 | I61: 23 | J61: therms | K61: 32.14
A62: 46013 | B62: 0.29166667 | C62: Xcel Energy | D62: 1 | F62: 955308634_ | H62: Sales Tax | K62: =2.24+1.24
A63: 46013
A64: 46013
A65: 46012 | B65: 0.49027778 | C65: Costco | E65: 1 | H65: Subaru Gas ? Gallons @ $?/gal | K65: 30.8
A66: 46011
A67: 46011
A68: 46010
A69: 46009 | B69: 0.64027778 | E69: 1 | H69: Subaru Gas ? Gallons @ $?/gal | K69: 4.6
A70: 46009
A71: 46009
A72: 46008
A73: 46008
A74: 46008
A75: 46008
A76: 46008
A77: 46008 | C77: Guard and Grace | E77: 1 | H77: EARMARK for Date!!! | I77: 1 | J77: cnt | K77: 300
A78: 46007 | B78: 0.72291667 | C78: Aurora Water | D78: 1 | F78: 0003677994_4671180824 | H78: First 5K GAL @$5.63/KGal | I78: 4 | J78: kGal | K78: 22.52
A79: 46007 | B79: 0.72291667 | C79: Aurora Water | D79: 1 | F79: 0003677994_4671180824 | H79: Sewer Usage Chg @$5.06/Kgal | I79: 3.33 | J79: kGal | K79: 16.85
A80: 46007 | B80: 0.72291667 | C80: Aurora Water | D80: 1 | F80: 0003677994_4671180824 | H80: Water Monthly Svc Chg 10/27-11/21 | K80: 14.94
A81: 46007 | B81: 0.72291667 | C81: Aurora Water | D81: 1 | F81: 0003677994_4671180824 | H81: Storm Drain Base | K81: 11.6
A82: 46007 | B82: 0.72291667 | C82: Aurora Water | D82: 1 | F82: 0003677994_4671180824 | H82: Sewer Monthly Svc Chg | K82: 5.51
A83: 46007
A84: 46007
A85: 46004 | B85: 0.96527778 | C85: Xfinity | D85: 1 | H85: Eli Xfinity Unlimited Line Phone Bill - 2nd month (Oct 24 - Nov 23) | K85: 40
A86: 46004 | B86: 0.96527778 | C86: Xfinity | D86: 1 | H86: **DISCOUNT** Xfinity 1 year promotion for free "unlimited phone line" | K86: -40
A87: 46003 | B87: 0.6953588 | C87: Five Guys | E87: 1 | F87: AAB8ZNC4ACA9 | H87: Little Hamburger: All the Way + raw onions, jalapeno peppers, grilled green peppers | I87: 1 | J87: cnt | K87: 8.19
A88: 46003 | B88: 0.6953588 | C88: Five Guys | E88: 1 | F88: AAB8ZNC4ACA9 | H88: Little Hamburger: Mayo, lettuce, pickles, EXTRA tomatoes, GRILLED green peppers | I88: 1 | J88: cnt | K88: 8.19
A89: 46003 | B89: 0.6953588 | C89: Five Guys | E89: 1 | F89: AAB8ZNC4ACA9 | H89: Sales Tax | I89: 2 | J89: cnt | K89: 1.35
A90: 46003 | B90: 0.48472222 | C90: Amazon | D90: 1 | F90: 111-2190174-3563423 | G90: A | H90: Standard Process Choline - Supports Healthy Fat Metabolism, Liver Health & Nervous System Function - Gluten-Free, Non-Dairy & Vegetarian -180 mg, 90 Tablets | I90: 90 | J90: cnt | K90: 17.6
A91: 46003 | B91: 0.48472222 | C91: Amazon | D91: 1 | F91: 111-2190174-3563423 | G91: A | H91: **DISCOUNT** Amazon Registry 15% discount | I91: 90 | J91: cnt | K91: -2.51
A92: 46003 | B92: 0.48472222 | C92: Amazon | D92: 1 | F92: 111-2190174-3563423 | G92: A | H92: **DISCOUNT** Save 5% auto-delivery scheduling | I92: 90 | J92: cnt | K92: -0.88
A93: 46003 | B93: 0.48472222 | C93: Amazon | D93: 1 | F93: 111-2190174-3563423 | G93: B | H93: New Chapter, Postnatal Vitamins Lactation Supplement, Complete Multivitamin with Fermented Vitamin D3 + B Vitamins, Made with Organic Vegetables & Herbs, Non-GMO Ingredients, 192 Count | I93: 192 | J93: cnt | K93: 35
A94: 46003 | B94: 0.48472222 | C94: Amazon | D94: 1 | F94: 111-2190174-3563423 | G94: B | H94: **DISCOUNT** Amazon Registry 15% discount | I94: 192 | J94: cnt | K94: -3.29
A95: 46003 | B95: 0.48472222 | C95: Amazon | D95: 1 | F95: 111-2190174-3563423 | G95: B | H95: **DISCOUNT** Save 5% auto-delivery scheduling | I95: 192 | J95: cnt | K95: -1.75
A96: 46003 | B96: 0.48472222 | C96: Amazon | D96: 1 | F96: 111-2190174-3563423 | G96: B | H96: **DISCOUNT** Amazon Promotional credit ? Is this from the wipes? | I96: 192 | J96: cnt | K96: -11.29
A97: 46003 | B97: 0.48472222 | C97: Amazon | D97: 1 | F97: 111-2190174-3563423 | G97: C | H97: Boncare 9 Seconds Digital Basal Thermometer - Accurate Oral & Rectal Thermometer for Adults & Kids, Fever Alarm, Large Display (Blue) | I97: 1 | J97: cnt | K97: 10.89
A98: 46003 | B98: 0.48472222 | C98: Amazon | D98: 1 | F98: 111-2190174-3563423 | G98: C | H98: **DISCOUNT** Amazon Promotional credit ? Is this from the wipes? | I98: 1 | J98: cnt | K98: -3.71
A99: 46003 | B99: 0.48472222 | C99: Amazon | D99: 1 | F99: 111-2190174-3563423 | G99: D | H99: TolleSonne 8 Pack Kids Artwork Frames Changeable, 8.5x11in Kids Art Frames Front Opening, Children Art Projects Kids Art Frames Picture Frames for Kids Drawing, Crafts and Photos, Holds 130 Pcs | I99: 8 | J99: cnt | K99: 73.99
A100: 46003 | B100: 0.48472222 | C100: Amazon | D100: 1 | F100: 111-2190174-3563423 | H100: Tax | I100: 4 | J100: cnt | K100: 9.32
...

Sheet ingredients
A1: Code | B1: Meal Name | C1: Ingredient | D1: Qt | E1: Unit | F1: Total | G1: CostTot | H1: CostQt
A2: A | B2: Mackerel Meatball | C2: Canned Mackerel | D2: 2 | E2: can | F2: 12 | G2: 17.71 | H2: =IFERROR(D2/F2*G2,0)
A3: A | B3: Mackerel Meatball | C3: Cucumber | D3: 0.66666667 | E3: cnt | F3: 3 | G3: 5.99 | H3: =IFERROR(D3/F3*G3,0)
A4: A | B4: Mackerel Meatball | C4: Dill | D4: 0.29 | E4: lb | F4: 1 | G4: 14.99 | H4: =IFERROR(D4/F4*G4,0)
A5: A | B5: Mackerel Meatball | C5: Egg | D5: 2 | E5: cnt | F5: 60 | G5: 9.39 | H5: =IFERROR(D5/F5*G5,0)
A6: A | B6: Mackerel Meatball | C6: Feta | D6: 0.5 | E6: cup | F6: 8 | G6: 6.99 | H6: =IFERROR(D6/F6*G6,0)
A7: A | B7: Mackerel Meatball | C7: Grapes | D7: 0.33333333 | E7: box | F7: 1 | G7: 5.89 | H7: =IFERROR(D7/F7*G7,0)
A8: A | B8: Mackerel Meatball | C8: Kale | D8: 1 | E8: bunch | F8: 3 | G8: 8.37 | H8: =IFERROR(D8/F8*G8,0)
A9: A | B9: Mackerel Meatball | C9: Lemon | D9: 1 | E9: cnt | F9: 1 | G9: 0.58 | H9: =IFERROR(D9/F9*G9,0)
A10: A | B10: Mackerel Meatball | C10: Lemon Juice | D10: 0.25 | E10: bottle | F10: 1 | G10: 1.69 | H10: =IFERROR(D10/F10*G10,0)
A11: A | B11: Mackerel Meatball | C11: Lime | D11: 1 | E11: cnt | F11: 1 | G11: 0.2 | H11: =IFERROR(D11/F11*G11,0)
A12: A | B12: Mackerel Meatball | C12: Olive Oil | D12: 4 | E12: tbsn | F12: 67.7 | G12: 27.99 | H12: =IFERROR(D12/F12*G12,0)
A13: A | B13: Mackerel Meatball | C13: Parsley | D13: 0.5 | E13: bunch | F13: 1 | G13: 0.99 | H13: =IFERROR(D13/F13*G13,0)
... A49: C | B49: Warm Chicken Grain Bowl | C49: Garlic Powder | D49: 2 | E49: tsp | F49: 60 | G49: 5.99 | H49: =IFERROR(D49/F49*G49,0)
A50: D | B50: Turkey Barley Soup | C50: Berries | D50: 9 | E50: oz | F50: 9 | G50: 2.98 | H50: =IFERROR(D41/F41*G41,0)
A51: D | B51: Turkey Barley Soup | C51: Carrots | D51: 1 | E51: lb | F51: 1 | G51: 0.98 | H51: =IFERROR(D42/F42*G42,0)
A52: D | B52: Turkey Barley Soup | C52: Carrots | D52: 1 | E52: lb | F52: 1 | G52: 0.98 | H52: =IFERROR(D43/F43*G43,0)
A53: D | B53: Turkey Barley Soup | C53: Celery | D53: 1 | E53: rib | F53: 4 | G53: 2.49 | H53: =IFERROR(D44/F44*G44,0)
A54: D | B54: Turkey Barley Soup | C54: ground turkey | D54: 1.72 | E54: lb | F54: 4 | G54: 24.99 | H54: =IFERROR(D45/F45*G45,0)
A55: D | B55: Turkey Barley Soup | C55: Parsley | D55: 0.5 | E55: bunch | F55: 1 | G55: 0.99 | H55: =IFERROR(D46/F46*G46,0)
A56: D | B56: Turkey Barley Soup | C56: pearl barley | D56: 1 | E56: bag | F56: 1 | G56: 1.58 | H56: =IFERROR(D47/F47*G47,0)
A57: D | B57: Turkey Barley Soup | C57: Purple Potato | D57: 2 | E57: lb | F57: 1 | G57: 2.49 | H57: =IFERROR(D48/F48*G48,0)
A58: D | B58: Turkey Barley Soup | C58: Salt and Pepper | D58: 0.25 | E58: tsp | F58: 26 | G58: 6.69 | H58: =IFERROR(D49/F49*G49,0)
A59: D | B59: Turkey Barley Soup | C59: Sourdough Bread | D59: 0.5 | E59: loaf | F59: 1 | G59: 4.5 | H59: =IFERROR(D50/F50*G50,0)
A60: D | B60: Turkey Barley Soup | C60: Tomato Sauce | D60: 1 | E60: can | F60: 12 | G60: 12.99 | H60: =IFERROR(D51/F51*G51,0)
A61: D | B61: Turkey Barley Soup | C61: Vegan Cheddar | D61: 2 | E61: slices | F61: 12 | G61: 6.99 | H61: =IFERROR(D52/F52*G52,0)
... A80: F | B80: Turkey Spaghetti | C80: Tomato Sauce | D80: 3 | E80: can | F80: 12 | G80: 12.99 | H80: =IFERROR(D71/F71*G71,0)
A81: Total | G81: =SUBTOTAL(109,Table31[CostTot]) | H81: =IFERROR(D72/F72*G72,0)
H82: =IFERROR(D73/F73*G73,0)
H83: =IFERROR(D74/F74*G74,0)
H84: =IFERROR(D75/F75*G75,0)
A85: Total | G85: =SUBTOTAL(109,Table31[CostTot]) | H85: =SUBTOTAL(109,Table31[CostQt])

Sheet totalMealCost
A1: Code | B1: Meal Name | C1: Total Meal Cost | D1: Servings | E1: Cost/Serving
A2: A | B2: Mackerel Meatball | C2: =SUMIF(ingredients!A:A,A2,ingredients!H:H) | D2: 5 | E2: =C2/D2
A3: B | B3: Kale & Chicken Pasta | C3: =SUMIF(ingredients!A:A,A3,ingredients!H:H) | D3: 6 | E3: =C3/D3
A4: C | B4: Warm Chicken Grain Bowl | C4: =SUMIF(ingredients!A:A,A4,ingredients!H:H) | D4: 8 | E4: =C4/D4
A5: D | B5: Chicken Barley Soup | C5: =SUMIF(ingredients!A:A,A5,ingredients!H:H) | D5: 8 | E5: =C5/D5
A6: E | B6: Mackerel Cauliflower Fried Rice | C6: =SUMIF(ingredients!A:A,A6,ingredients!H:H) | D6: 6 | E6: =C6/D6
A7: F | B7: Turkey Spaghetti | C7: =SUMIF(ingredients!A:A,A7,ingredients!H:H) | D7: 6 | E7: =C7/D7
